setup.cfg
setup.py
zilingo_recomm_utils/DataPreparation.py
zilingo_recomm_utils/__init__.py
zilingo_recomm_utils.egg-info/PKG-INFO
zilingo_recomm_utils.egg-info/SOURCES.txt
zilingo_recomm_utils.egg-info/dependency_links.txt
zilingo_recomm_utils.egg-info/not-zip-safe
zilingo_recomm_utils.egg-info/top_level.txt
zilingo_recomm_utils.egg-info/.ipynb_checkpoints/SOURCES-checkpoint.txt
zilingo_recomm_utils.egg-info/.ipynb_checkpoints/dependency_links-checkpoint.txt
zilingo_recomm_utils.egg-info/.ipynb_checkpoints/not-zip-safe-checkpoint
zilingo_recomm_utils.egg-info/.ipynb_checkpoints/top_level-checkpoint.txt