Metadata-Version: 1.0
Name: zilingo-recomm-utils
Version: 0.0.2
Summary: recommendation utils
Home-page: UNKNOWN
Author: UNKNOWN
Author-email: himanshu.jain@zilingo.com
License: UNKNOWN
Platform: UNKNOWN
